README.md
setup.cfg
setup.py
rcl/__init__.py
rcl/helpers.py
rcl/main.py
rcl.egg-info/PKG-INFO
rcl.egg-info/SOURCES.txt
rcl.egg-info/dependency_links.txt
rcl.egg-info/entry_points.txt
rcl.egg-info/requires.txt
rcl.egg-info/top_level.txt