Metadata-Version: 2.1
Name: rcl
Version: 0.1.2
Summary: A simple command line wrapper for rclone focused on easy folder syncing
Home-page: https://github.com/Ben-Ryder/rcl
Author: Ben Ryder
Author-email: dev@benryder.me
License: GPLV3
Download-URL: https://github.com/Ben-Ryder/rcl/archive/v0.1.2.tar.gz
Keywords: rclone,rclone-wrapper
Platform: UNKNOWN
Classifier: Development Status :: 3 - Alpha
Classifier: License :: OSI Approved :: GNU General Public License v3 (GPLv3)
Classifier: Operating System :: POSIX :: Linux
Classifier: Operating System :: MacOS
